[{
  "_id": {
    "$oid": "6328575aabebb68fafccc244"
  },
  "西安市铁一中学": [
    108.973766,
    34.240043
  ],
  "西安市第八中学": [
    108.960614,
    34.255601
  ],
  "西安翱翔中学": [
    108.916408,
    34.239391
  ],
  "尊德中学": [
    108.982458,
    34.263262
  ],
  "西安市第六中学": [
    108.937352,
    34.256403
  ],
  "西安市第二十六中学": [
    108.966332,
    34.257017
  ],
  "西安市第八十二中学": [
    108.926743,
    34.240268
  ],
  "西安市第十二中学": [
    108.967412,
    34.248624
  ],
  "西安市第六中学分校": [
    108.942746,
    34.244353
  ],
  "西安市第八十六中学": [
    108.958536,
    34.24433
  ],
  "西安市第三中学分校": [
    108.989802,
    34.263477
  ],
  "西安市第六中学南校区": [
    108.942165,
    34.244368
  ],
  "西安市第二十六中学分校": [
    108.957556,
    34.250439
  ],
  "西安市第三中学": [
    108.983863,
    34.264568
  ],
  "西北工业大学附属中学(高中部)": [
    108.918706,
    34.241862
  ],
  "西北工业大学附属中学含光校区": [
    108.931337,
    34.246719
  ],
  "西安民兴中学": [
    108.960139,
    34.25431
  ],
  "西安西北中学": [
    108.937868,
    34.252776
  ],
  "西安工业大学附属中学": [
    108.997584,
    34.264335
  ],
  "西北工业大学附属中学": [
    108.9195,
    34.241871
  ],
  "西安市中铁中学": [
    108.971368,
    34.239245
  ],
  "西安市第三中学(第二分校)": [
    108.97865,
    34.257474
  ],
  "铁一中学联合总校西安工业大学附中分校": [
    108.997723,
    34.264272
  ],
  "西安建筑科技大学附属中学": [
    108.969971,
    34.233991
  ],
  "西安市第七十一中学": [
    108.957815,
    34.242107
  ],
  "西安市第二十六中学太乙分校": [
    108.972109,
    34.245256
  ],
  "西安交通大学附属中学-初中部": [
    108.988565,
    34.24697
  ],
  "西北大学附属中学": [
    108.920662,
    34.247665
  ],
  "大学南路小学": [
    108.928377,
    34.245477
  ],
  "南门小学": [
    108.947621,
    34.243826
  ],
  "振兴路小学": [
    108.943287,
    34.246938
  ],
  "西安市碑林区建国路小学": [
    108.966378,
    34.256143
  ],
  "文艺路小学": [
    108.952786,
    34.243065
  ],
  "西安建筑科技大学附属小学": [
    108.96954,
    34.234153
  ],
  "东关南街小学": [
    108.973784,
    34.257502
  ],
  "西北工业大学附属小学": [
    108.916939,
    34.245681
  ],
  "西安市碑林区铁五小学": [
    108.977587,
    34.23894
  ],
  "西安市碑林区雁塔路小学": [
    108.959672,
    34.24463
  ],
  "东羊市小学": [
    108.962358,
    34.256579
  ],
  "乐居厂小学": [
    108.976561,
    34.245456
  ],
  "西荷小学": [
    108.927924,
    34.233558
  ],
  "大学南路小学(分校)": [
    108.927413,
    34.237661
  ],
  "西安市碑林区永宁小学": [
    108.98474,
    34.260116
  ],
  "碑林区小雁塔小学": [
    108.940399,
    34.239822
  ],
  "长乐坊小学": [
    108.975972,
    34.264412
  ],
  "沙坡小学": [
    108.991353,
    34.243927
  ],
  "东关小学": [
    108.978269,
    34.258502
  ],
  "陕西省西安师范附属小学": [
    108.94845,
    34.253519
  ],
  "西安市碑林区兴庆小学": [
    108.993891,
    34.262375
  ],
  "西北大学附属小学": [
    108.920754,
    34.247672
  ],
  "西安市碑林区铁五小学(南校区)": [
    108.975132,
    34.236224
  ],
  "钟楼小学": [
    108.945168,
    34.256895
  ],
  "西安市碑林区东厅门小学": [
    108.957867,
    34.255743
  ],
  "永新小学": [
    108.97632,
    34.263778
  ],
  "西安交通大学附属小学兴庆校区": [
    108.994771,
    34.250343
  ],
  "景龙池小学": [
    108.984733,
    34.262351
  ],
  "西安市新城区普天小学": [
    109.003095,
    34.248994
  ],
  "碑林区何家村小学": [
    108.928107,
    34.233658
  ],
  "小时候第一小学(钟楼店)": [
    108.950373,
    34.256103
  ],
  "大学南路小学(朱雀分校)": [
    108.938099,
    34.245705
  ],
  "西安市碑林区铁五第二小学": [
    108.975015,
    34.236103
  ],
  "新文达教育中小学交大校区": [
    108.987913,
    34.249704
  ],
  "西安市碑林区实验小学": [
    108.968941,
    34.248939
  ],
  "仁厚庄小学": [
    108.993472,
    34.256651
  ],
  "西安市碑林区友谊小学": [
    108.958766,
    34.23933
  ]
}]